django_restql/__init__.py
django_restql/exceptions.py
django_restql/fields.py
django_restql/mixins.py
django_restql/operations.py
django_restql/parser.py
django_restql/serializers.py
django_restql/settings.py
django_restql-0.18.0.dist-info/LICENSE
django_restql-0.18.0.dist-info/METADATA
django_restql-0.18.0.dist-info/WHEEL
django_restql-0.18.0.dist-info/top_level.txt
django_restql-0.18.0.dist-info/RECORD
